{"type":"transitive","from":"USDC","amountIn":12.210448931437512,"mid":"PAI","amountMid":12.340252,"to":"USDC","amountOut":7.003517,"amountWithFees":7.000015241500001,"minimumReceived":6.965015165292501,"providers":["saber","saber"],"fees":{"PAI":0.006170126000000001,"USDC":0.003501758500000001},"priceImpact":0.42300875520430503,"priceDisplay":0.5735675272322269,"split":[1,1],"routeData":{"route1":{"from":"USDC","amountIn":12.210448931437512,"to":"PAI","amountOut":12.340252,"amountWithFees":12.334081874,"minimumReceived":12.27241146463,"provider":"saber","fees":{"PAI":0.006170126000000001},"priceImpact":0.000009408801017160682,"routeData":{"saberInfo":{"stableSwap":{"config":{"swapAccount":"B2izdXFYb2sNwbWWHmh75T4aQFtfXsUxem9u2p61HGzf","swapProgramID":"SSwpkEEcbUqx4vtoEByFjSkhKdCT862DNVb52nZg1UZ","tokenProgramID":"TokenkegQfeZyiNwAJbNbGKPFXCWuBvf9Ss623VQ5DA","authority":"7W9KMACQT6UmjRPEUQKXyVf4NjZ9Ux4PHs1e1P5PxDtA"},"state":{"isInitialized":true,"isPaused":false,"nonce":255,"futureAdminDeadline":0,"futureAdminAccount":"11111111111111111111111111111111","adminAccount":"2NGhdqVQJbt8vkKEr7faxjok8p1NEQ9o1p2FQWAuthLS","tokenA":{"adminFeeAccount":"ECA38NDxPqwo5997B34JL7UkC3VZSQMzRGHThetgFDwC","reserve":"4DYwgJtxwuJdAjkj5RJSNH4e7U329V5cNp7d3a1nLrZv","mint":"Ea5SjE2Y6yvCeW5dYTn7PYMuW5ikXkvbGdcmSnXeaLjS"},"tokenB":{"adminFeeAccount":"qRMfgjGkq7ribEdJtWm3FUCpzCkS2Mguh7WXshChttR","reserve":"EXNW64GEf1ACC6xY9BtKRiunrs6GoJSXBdxWN2eTPmrF","mint":"EPjFWdd5AufqSSqeM2qN1xzybapC8G4wEGGkZwyTDt1v"},"poolTokenMint":"PaiYwHYxr4SsEWox9YmyBNJmxVG7GdauirbBcYGB7cJ","initialAmpFactor":"96","targetAmpFactor":"96","startRampTimestamp":0,"stopRampTimestamp":0,"fees":{"adminTrade":{"isFraction":true,"numeratorStr":"0","denominatorStr":"10000000","isPercent":true},"adminWithdraw":{"isFraction":true,"numeratorStr":"0","denominatorStr":"10000000","isPercent":true},"trade":{"isFraction":true,"numeratorStr":"1","denominatorStr":"100000","isPercent":true},"withdraw":{"isFraction":true,"numeratorStr":"0","denominatorStr":"10000000","isPercent":true}}}},"reserveA":{"publicKey":"4DYwgJtxwuJdAjkj5RJSNH4e7U329V5cNp7d3a1nLrZv","account":{"data":{"type":"Buffer","data":[201,161,31,1,204,133,126,95,235,221,255,159,217,224,76,200,47,68,236,88,236,111,25,226,63,94,124,202,7,255,176,65,96,157,94,75,31,250,138,237,38,122,228,47,64,174,43,197,76,118,26,142,35,72,26,230,92,29,77,206,21,120,180,63,71,196,14,223,43,4,0,0,0,0,0,0,0,0,0,0,0,0,0,0,0,0,0,0,0,0,0,0,0,0,0,0,0,0,0,0,0,0,0,0,0,0,0,0,1,0,0,0,0,0,0,0,0,0,0,0,0,0,0,0,0,0,0,0,0,0,0,0,0,0,0,0,0,0,0,0,0,0,0,0,0,0,0,0,0,0,0,0,0,0,0,0,0,0,0,0,0,0,0,0,0]},"executable":false,"lamports":2039280,"owner":"TokenkegQfeZyiNwAJbNbGKPFXCWuBvf9Ss623VQ5DA","rentEpoch":361}},"reserveB":{"publicKey":"EXNW64GEf1ACC6xY9BtKRiunrs6GoJSXBdxWN2eTPmrF","account":{"data":{"type":"Buffer","data":[198,250,122,243,190,219,173,58,61,101,243,106,171,201,116,49,177,187,228,194,210,246,224,228,124,166,2,3,69,47,93,97,96,157,94,75,31,250,138,237,38,122,228,47,64,174,43,197,76,118,26,142,35,72,26,230,92,29,77,206,21,120,180,63,159,243,130,156,120,1,0,0,0,0,0,0,0,0,0,0,0,0,0,0,0,0,0,0,0,0,0,0,0,0,0,0,0,0,0,0,0,0,0,0,0,0,0,0,1,0,0,0,0,0,0,0,0,0,0,0,0,0,0,0,0,0,0,0,0,0,0,0,0,0,0,0,0,0,0,0,0,0,0,0,0,0,0,0,0,0,0,0,0,0,0,0,0,0,0,0,0,0,0,0,0]},"executable":false,"lamports":2039280,"owner":"TokenkegQfeZyiNwAJbNbGKPFXCWuBvf9Ss623VQ5DA","rentEpoch":361}},"exchange":{"swapAccount":"B2izdXFYb2sNwbWWHmh75T4aQFtfXsUxem9u2p61HGzf","programID":"SSwpkEEcbUqx4vtoEByFjSkhKdCT862DNVb52nZg1UZ","lpToken":{"symbol":"SLP","name":"A-B Saber LP","logoURI":"https://app.saber.so/tokens/slp.png","decimals":0,"address":"PaiYwHYxr4SsEWox9YmyBNJmxVG7GdauirbBcYGB7cJ","chainId":101,"tags":["saber-stableswap-lp"]},"tokens":[{"chainId":101,"address":"Ea5SjE2Y6yvCeW5dYTn7PYMuW5ikXkvbGdcmSnXeaLjS","name":"A","decimals":0,"symbol":"A"},{"chainId":101,"address":"EPjFWdd5AufqSSqeM2qN1xzybapC8G4wEGGkZwyTDt1v","name":"B","decimals":0,"symbol":"B"}]},"exchangeInfo":{"ampFactor":[150],"fees":{"adminTrade":{"isFraction":true,"numeratorStr":"0","denominatorStr":"10000000","isPercent":true},"adminWithdraw":{"isFraction":true,"numeratorStr":"0","denominatorStr":"10000000","isPercent":true},"trade":{"isFraction":true,"numeratorStr":"1","denominatorStr":"100000","isPercent":true},"withdraw":{"isFraction":true,"numeratorStr":"0","denominatorStr":"10000000","isPercent":true}},"lpTotalSupply":{"isFraction":true,"numeratorStr":"0","denominatorStr":"1","_isTA":true,"mint":"PaiYwHYxr4SsEWox9YmyBNJmxVG7GdauirbBcYGB7cJ","uiAmount":"0"},"reserves":[{"reserveAccount":"4DYwgJtxwuJdAjkj5RJSNH4e7U329V5cNp7d3a1nLrZv","adminFeeAccount":"ECA38NDxPqwo5997B34JL7UkC3VZSQMzRGHThetgFDwC","amount":{"isFraction":true,"numeratorStr":"4586472391751","denominatorStr":"1","_isTA":true,"mint":"Ea5SjE2Y6yvCeW5dYTn7PYMuW5ikXkvbGdcmSnXeaLjS","uiAmount":"4586472391751"}},{"reserveAccount":"EXNW64GEf1ACC6xY9BtKRiunrs6GoJSXBdxWN2eTPmrF","adminFeeAccount":"qRMfgjGkq7ribEdJtWm3FUCpzCkS2Mguh7WXshChttR","amount":{"isFraction":true,"numeratorStr":"1617533531039","denominatorStr":"1","_isTA":true,"mint":"EPjFWdd5AufqSSqeM2qN1xzybapC8G4wEGGkZwyTDt1v","uiAmount":"1617533531039"}}]}},"fromCoin":{"symbol":"USDC","decimals":6,"mintAddress":"EPjFWdd5AufqSSqeM2qN1xzybapC8G4wEGGkZwyTDt1v","coingeckoId":"usd-coin","chainId":101,"address":"EPjFWdd5AufqSSqeM2qN1xzybapC8G4wEGGkZwyTDt1v","name":"USD Coin","logoURI":"https://raw.githubusercontent.com/solana-labs/token-list/main/assets/mainnet/EPjFWdd5AufqSSqeM2qN1xzybapC8G4wEGGkZwyTDt1v/logo.png","tags":["stablecoin"],"extensions":{"coingeckoId":"usd-coin","serumV3Usdt":"77quYg4MGneUdjgXCunt9GgM1usmrxKY31twEy3WHwcS","website":"https://www.centre.io/"}},"toCoin":{"symbol":"PAI","decimals":6,"mintAddress":"Ea5SjE2Y6yvCeW5dYTn7PYMuW5ikXkvbGdcmSnXeaLjS","coingeckoId":"parrot-usd","chainId":101,"address":"Ea5SjE2Y6yvCeW5dYTn7PYMuW5ikXkvbGdcmSnXeaLjS","name":"PAI (Parrot USD)","logoURI":"https://raw.githubusercontent.com/solana-labs/token-list/main/assets/mainnet/Ea5SjE2Y6yvCeW5dYTn7PYMuW5ikXkvbGdcmSnXeaLjS/logo.svg","tags":["utility-token","stablecoin"],"extensions":{"coingeckoId":"parrot-usd","discord":"https://discord.gg/gopartyparrot","medium":"https://gopartyparrot.medium.com/","telegram":"https://t.me/gopartyparrot","twitter":"https://twitter.com/gopartyparrot","website":"https://parrot.fi"}}}},"route2":{"from":"PAI","amountIn":12.340252,"to":"USDC","amountOut":7.003517,"amountWithFees":7.000015241500001,"minimumReceived":6.965015165292501,"provider":"saber","fees":{"USDC":0.003501758500000001},"priceImpact":0.42300875520430503,"routeData":{"saberInfo":{"stableSwap":{"config":{"swapAccount":"4vezWG46exH6pf9nry3n1VJ7hZHvjBJNgNeF4qEFCML5","swapProgramID":"SSwpkEEcbUqx4vtoEByFjSkhKdCT862DNVb52nZg1UZ","tokenProgramID":"TokenkegQfeZyiNwAJbNbGKPFXCWuBvf9Ss623VQ5DA","authority":"CBoqZomuxiKptaYxTdsfXooHPSeQhKqwB9Tm1TMxa43g"},"state":{"isInitialized":true,"isPaused":false,"nonce":249,"futureAdminDeadline":0,"futureAdminAccount":"11111111111111111111111111111111","adminAccount":"H9XuKqszWYirDmXDQ12TZXGtxqUYYn4oi7FKzAm7RHGc","tokenA":{"adminFeeAccount":"CLnxgJfRyRPasyVHZtmH8bZEnEtPRfkffm3KeHEEMHzA","reserve":"3Pg5xVmLQQm4nHMJ4ATXXKWejkw3chJnLnJVng2rAszu","mint":"EPjFWdd5AufqSSqeM2qN1xzybapC8G4wEGGkZwyTDt1v"},"tokenB":{"adminFeeAccount":"5L3UbgyV8rMqzJNnqz7ifdAfx4L8CTxAnUdvHFg4mHM4","reserve":"DPhWpkh39jo45PiGPois7Qs3Z8KcsqZY2dHZo7faVCEP","mint":"Ea5SjE2Y6yvCeW5dYTn7PYMuW5ikXkvbGdcmSnXeaLjS"},"poolTokenMint":"SPaiZAYyJBQHaSjtxFBKtLtQiCuG328r1mTfmvvydR5","initialAmpFactor":"01","targetAmpFactor":"01","startRampTimestamp":0,"stopRampTimestamp":0,"fees":{"adminTrade":{"isFraction":true,"numeratorStr":"0","denominatorStr":"10000","isPercent":true},"adminWithdraw":{"isFraction":true,"numeratorStr":"0","denominatorStr":"10000","isPercent":true},"trade":{"isFraction":true,"numeratorStr":"4","denominatorStr":"10000","isPercent":true},"withdraw":{"isFraction":true,"numeratorStr":"0","denominatorStr":"10000","isPercent":true}}}},"reserveA":{"publicKey":"3Pg5xVmLQQm4nHMJ4ATXXKWejkw3chJnLnJVng2rAszu","account":{"data":{"type":"Buffer","data":[198,250,122,243,190,219,173,58,61,101,243,106,171,201,116,49,177,187,228,194,210,246,224,228,124,166,2,3,69,47,93,97,166,53,82,204,45,183,32,1,155,167,87,44,74,128,15,107,46,17,25,142,26,175,33,209,213,15,67,41,188,237,72,159,8,169,151,0,0,0,0,0,0,0,0,0,0,0,0,0,0,0,0,0,0,0,0,0,0,0,0,0,0,0,0,0,0,0,0,0,0,0,0,0,0,0,0,0,1,0,0,0,0,0,0,0,0,0,0,0,0,0,0,0,0,0,0,0,0,0,0,0,0,0,0,0,0,0,0,0,0,0,0,0,0,0,0,0,0,0,0,0,0,0,0,0,0,0,0,0,0,0,0,0,0]},"executable":false,"lamports":2039280,"owner":"TokenkegQfeZyiNwAJbNbGKPFXCWuBvf9Ss623VQ5DA","rentEpoch":361}},"reserveB":{"publicKey":"DPhWpkh39jo45PiGPois7Qs3Z8KcsqZY2dHZo7faVCEP","account":{"data":{"type":"Buffer","data":[201,161,31,1,204,133,126,95,235,221,255,159,217,224,76,200,47,68,236,88,236,111,25,226,63,94,124,202,7,255,176,65,166,53,82,204,45,183,32,1,155,167,87,44,74,128,15,107,46,17,25,142,26,175,33,209,213,15,67,41,188,237,72,159,48,25,155,0,0,0,0,0,0,0,0,0,0,0,0,0,0,0,0,0,0,0,0,0,0,0,0,0,0,0,0,0,0,0,0,0,0,0,0,0,0,0,0,0,1,0,0,0,0,0,0,0,0,0,0,0,0,0,0,0,0,0,0,0,0,0,0,0,0,0,0,0,0,0,0,0,0,0,0,0,0,0,0,0,0,0,0,0,0,0,0,0,0,0,0,0,0,0,0,0,0]},"executable":false,"lamports":2039280,"owner":"TokenkegQfeZyiNwAJbNbGKPFXCWuBvf9Ss623VQ5DA","rentEpoch":361}},"exchange":{"swapAccount":"4vezWG46exH6pf9nry3n1VJ7hZHvjBJNgNeF4qEFCML5","programID":"SSwpkEEcbUqx4vtoEByFjSkhKdCT862DNVb52nZg1UZ","lpToken":{"symbol":"SLP","name":"A-B Saber LP","logoURI":"https://app.saber.so/tokens/slp.png","decimals":0,"address":"SPaiZAYyJBQHaSjtxFBKtLtQiCuG328r1mTfmvvydR5","chainId":101,"tags":["saber-stableswap-lp"]},"tokens":[{"chainId":101,"address":"EPjFWdd5AufqSSqeM2qN1xzybapC8G4wEGGkZwyTDt1v","name":"A","decimals":0,"symbol":"A"},{"chainId":101,"address":"Ea5SjE2Y6yvCeW5dYTn7PYMuW5ikXkvbGdcmSnXeaLjS","name":"B","decimals":0,"symbol":"B"}]},"exchangeInfo":{"ampFactor":[1],"fees":{"adminTrade":{"isFraction":true,"numeratorStr":"0","denominatorStr":"10000","isPercent":true},"adminWithdraw":{"isFraction":true,"numeratorStr":"0","denominatorStr":"10000","isPercent":true},"trade":{"isFraction":true,"numeratorStr":"4","denominatorStr":"10000","isPercent":true},"withdraw":{"isFraction":true,"numeratorStr":"0","denominatorStr":"10000","isPercent":true}},"lpTotalSupply":{"isFraction":true,"numeratorStr":"0","denominatorStr":"1","_isTA":true,"mint":"SPaiZAYyJBQHaSjtxFBKtLtQiCuG328r1mTfmvvydR5","uiAmount":"0"},"reserves":[{"reserveAccount":"3Pg5xVmLQQm4nHMJ4ATXXKWejkw3chJnLnJVng2rAszu","adminFeeAccount":"CLnxgJfRyRPasyVHZtmH8bZEnEtPRfkffm3KeHEEMHzA","amount":{"isFraction":true,"numeratorStr":"9939208","denominatorStr":"1","_isTA":true,"mint":"EPjFWdd5AufqSSqeM2qN1xzybapC8G4wEGGkZwyTDt1v","uiAmount":"9939208"}},{"reserveAccount":"DPhWpkh39jo45PiGPois7Qs3Z8KcsqZY2dHZo7faVCEP","adminFeeAccount":"5L3UbgyV8rMqzJNnqz7ifdAfx4L8CTxAnUdvHFg4mHM4","amount":{"isFraction":true,"numeratorStr":"10164528","denominatorStr":"1","_isTA":true,"mint":"Ea5SjE2Y6yvCeW5dYTn7PYMuW5ikXkvbGdcmSnXeaLjS","uiAmount":"10164528"}}]}},"fromCoin":{"symbol":"PAI","decimals":6,"mintAddress":"Ea5SjE2Y6yvCeW5dYTn7PYMuW5ikXkvbGdcmSnXeaLjS","coingeckoId":"parrot-usd","chainId":101,"address":"Ea5SjE2Y6yvCeW5dYTn7PYMuW5ikXkvbGdcmSnXeaLjS","name":"PAI (Parrot USD)","logoURI":"https://raw.githubusercontent.com/solana-labs/token-list/main/assets/mainnet/Ea5SjE2Y6yvCeW5dYTn7PYMuW5ikXkvbGdcmSnXeaLjS/logo.svg","tags":["utility-token","stablecoin"],"extensions":{"coingeckoId":"parrot-usd","discord":"https://discord.gg/gopartyparrot","medium":"https://gopartyparrot.medium.com/","telegram":"https://t.me/gopartyparrot","twitter":"https://twitter.com/gopartyparrot","website":"https://parrot.fi"}},"toCoin":{"symbol":"USDC","decimals":6,"mintAddress":"EPjFWdd5AufqSSqeM2qN1xzybapC8G4wEGGkZwyTDt1v","coingeckoId":"usd-coin","chainId":101,"address":"EPjFWdd5AufqSSqeM2qN1xzybapC8G4wEGGkZwyTDt1v","name":"USD Coin","logoURI":"https://raw.githubusercontent.com/solana-labs/token-list/main/assets/mainnet/EPjFWdd5AufqSSqeM2qN1xzybapC8G4wEGGkZwyTDt1v/logo.png","tags":["stablecoin"],"extensions":{"coingeckoId":"usd-coin","serumV3Usdt":"77quYg4MGneUdjgXCunt9GgM1usmrxKY31twEy3WHwcS","website":"https://www.centre.io/"}}}},"fromCoin":{"symbol":"USDC","decimals":6,"mintAddress":"EPjFWdd5AufqSSqeM2qN1xzybapC8G4wEGGkZwyTDt1v","coingeckoId":"usd-coin","chainId":101,"address":"EPjFWdd5AufqSSqeM2qN1xzybapC8G4wEGGkZwyTDt1v","name":"USD Coin","logoURI":"https://raw.githubusercontent.com/solana-labs/token-list/main/assets/mainnet/EPjFWdd5AufqSSqeM2qN1xzybapC8G4wEGGkZwyTDt1v/logo.png","tags":["stablecoin"],"extensions":{"coingeckoId":"usd-coin","serumV3Usdt":"77quYg4MGneUdjgXCunt9GgM1usmrxKY31twEy3WHwcS","website":"https://www.centre.io/"}},"midCoin":{"symbol":"PAI","decimals":6,"mintAddress":"Ea5SjE2Y6yvCeW5dYTn7PYMuW5ikXkvbGdcmSnXeaLjS","coingeckoId":"parrot-usd","chainId":101,"address":"Ea5SjE2Y6yvCeW5dYTn7PYMuW5ikXkvbGdcmSnXeaLjS","name":"PAI (Parrot USD)","logoURI":"https://raw.githubusercontent.com/solana-labs/token-list/main/assets/mainnet/Ea5SjE2Y6yvCeW5dYTn7PYMuW5ikXkvbGdcmSnXeaLjS/logo.svg","tags":["utility-token","stablecoin"],"extensions":{"coingeckoId":"parrot-usd","discord":"https://discord.gg/gopartyparrot","medium":"https://gopartyparrot.medium.com/","telegram":"https://t.me/gopartyparrot","twitter":"https://twitter.com/gopartyparrot","website":"https://parrot.fi"}},"toCoin":{"symbol":"USDC","decimals":6,"mintAddress":"EPjFWdd5AufqSSqeM2qN1xzybapC8G4wEGGkZwyTDt1v","coingeckoId":"usd-coin","chainId":101,"address":"EPjFWdd5AufqSSqeM2qN1xzybapC8G4wEGGkZwyTDt1v","name":"USD Coin","logoURI":"https://raw.githubusercontent.com/solana-labs/token-list/main/assets/mainnet/EPjFWdd5AufqSSqeM2qN1xzybapC8G4wEGGkZwyTDt1v/logo.png","tags":["stablecoin"],"extensions":{"coingeckoId":"usd-coin","serumV3Usdt":"77quYg4MGneUdjgXCunt9GgM1usmrxKY31twEy3WHwcS","website":"https://www.centre.io/"}}}}